README.txt
setup.py
Products/__init__.py
Products.CMFActionIcons.egg-info/PKG-INFO
Products.CMFActionIcons.egg-info/SOURCES.txt
Products.CMFActionIcons.egg-info/dependency_links.txt
Products.CMFActionIcons.egg-info/entry_points.txt
Products.CMFActionIcons.egg-info/namespace_packages.txt
Products.CMFActionIcons.egg-info/not-zip-safe
Products.CMFActionIcons.egg-info/requires.txt
Products.CMFActionIcons.egg-info/test_info.txt
Products.CMFActionIcons.egg-info/top_level.txt
Products/CMFActionIcons/ActionIconsTool.py
Products/CMFActionIcons/CHANGES.txt
Products/CMFActionIcons/COPYRIGHT.txt
Products/CMFActionIcons/LICENSE.txt
Products/CMFActionIcons/README.txt
Products/CMFActionIcons/__init__.py
Products/CMFActionIcons/configure.zcml
Products/CMFActionIcons/exportimport.py
Products/CMFActionIcons/permissions.py
Products/CMFActionIcons/standard_mappings.py
Products/CMFActionIcons/tool.gif
Products/CMFActionIcons/version.txt
Products/CMFActionIcons/interfaces/__init__.py
Products/CMFActionIcons/interfaces/_tools.py
Products/CMFActionIcons/profiles/actionicons/actionicons.xml
Products/CMFActionIcons/profiles/actionicons/componentregistry.xml
Products/CMFActionIcons/profiles/actionicons/export_steps.xml
Products/CMFActionIcons/profiles/actionicons/import_steps.xml
Products/CMFActionIcons/profiles/actionicons/metadata.xml
Products/CMFActionIcons/profiles/actionicons/skins.xml
Products/CMFActionIcons/profiles/actionicons/toolset.xml
Products/CMFActionIcons/skins/actionicons/actionicons_macros.pt
Products/CMFActionIcons/skins/actionicons/approve_icon.png
Products/CMFActionIcons/skins/actionicons/edit_icon.png
Products/CMFActionIcons/skins/actionicons/expire_icon.png
Products/CMFActionIcons/skins/actionicons/folder_icon.png
Products/CMFActionIcons/skins/actionicons/metadata_icon.png
Products/CMFActionIcons/skins/actionicons/policies_icon.png
Products/CMFActionIcons/skins/actionicons/preview_icon.png
Products/CMFActionIcons/skins/actionicons/reject_icon.png
Products/CMFActionIcons/skins/actionicons/retract_icon.png
Products/CMFActionIcons/skins/actionicons/submit_icon.png
Products/CMFActionIcons/skins/actionicons/undo_icon.png
Products/CMFActionIcons/skins/actionicons/user_icon.png
Products/CMFActionIcons/skins/actionicons/worklist_icon.png
Products/CMFActionIcons/skins/actionicons/yank_icon.png
Products/CMFActionIcons/tests/__init__.py
Products/CMFActionIcons/tests/test_ActionIconsTool.py
